lib/__init__.py
lib/mortgage.py
mortgage_boi/__init__.py
mortgage_boi/mortgage.py
mortgage_boi-0.0.4.dist-info/LICENSE
mortgage_boi-0.0.4.dist-info/METADATA
mortgage_boi-0.0.4.dist-info/WHEEL
mortgage_boi-0.0.4.dist-info/top_level.txt
mortgage_boi-0.0.4.dist-info/RECORD
