Metadata-Version: 2.1
Name: mortgage-boi
Version: 0.0.4
Summary: A package for calculating mortgage data and cash flows
Home-page: https://github.com/charliereese/mortgage_boi
Author: Charlie Reese
Author-email: j.charles.reese@gmail.com
License: UNKNOWN
Platform: UNKNOWN
Classifier: Programming Language :: Python :: 3
Classifier: License :: OSI Approved :: MIT License
Classifier: Intended Audience :: Financial and Insurance Industry
Classifier: Operating System :: OS Independent
Classifier: Development Status :: 2 - Pre-Alpha
Requires-Python: >=3.6
